testbench_tuna/__init__.py
testbench_tuna/main.py
testbench_tuna/py.typed
testbench_tuna/utils.py
testbench_tuna-0.3.0.dist-info/LICENSE
testbench_tuna-0.3.0.dist-info/WHEEL
testbench_tuna-0.3.0.dist-info/METADATA
testbench_tuna-0.3.0.dist-info/RECORD
