Metadata-Version: 2.1
Name: testbench-tuna
Version: 0.3.0
Summary: Personal testbench for trying out stuff
Home-page: https://github.com/trallnag/testbench-tuna
License: ISC
Author: Tim Schwenke
Author-email: tim.schwenke@trallnag.com
Requires-Python: >=3.7,<4.0
Classifier: License :: OSI Approved
Classifier: Programming Language :: Python :: 3
Classifier: Programming Language :: Python :: 3.7
Classifier: Programming Language :: Python :: 3.8
Classifier: Programming Language :: Python :: 3.9
Classifier: Programming Language :: Python :: 3.10
Requires-Dist: fastapi (>=0.81.0,<0.82.0)
Requires-Dist: requests (>=2.28.1,<3.0.0)
Requires-Dist: uvicorn (>=0.18.2,<0.19.0)
Project-URL: Repository, https://github.com/trallnag/testbench-tuna
